pynumint.py
pynumint-0.2.3.dist-info/LICENSE
pynumint-0.2.3.dist-info/METADATA
pynumint-0.2.3.dist-info/WHEEL
pynumint-0.2.3.dist-info/top_level.txt
pynumint-0.2.3.dist-info/RECORD
