Metadata-Version: 2.1
Name: pynumint
Version: 0.2.3
Summary: pynumint is a package for Numerical Integration tasks
Home-page: https://github.com/CodeSleuthX/pynumint
Author: Arjun Jagdale
Author-email: arjunjagdale14@gmail.com
License: UNKNOWN
Project-URL: Bug Reports, https://github.com/CodeSleuthX/pynumint/issues
Project-URL: Source, https://github.com/CodeSleuthX/pynumint
Keywords: numerical integration mathematics science
Platform: UNKNOWN
Classifier: Programming Language :: Python :: 3
Classifier: License :: OSI Approved :: MIT License
Classifier: Operating System :: OS Independent
Classifier: Development Status :: 4 - Beta
Classifier: Intended Audience :: Developers
Classifier: Intended Audience :: Science/Research
Classifier: Topic :: Scientific/Engineering :: Mathematics
Classifier: Topic :: Software Development :: Libraries :: Python Modules
Requires-Python: >=3.6
License-File: LICENSE
Requires-Dist: numpy (>=1.18.0)
Provides-Extra: dev
Requires-Dist: check-manifest ; extra == 'dev'
Requires-Dist: flake8 ; extra == 'dev'
Provides-Extra: test
Requires-Dist: coverage ; extra == 'test'
